dtalk_robot/__init__.py
dtalk_robot/request/__init__.py
dtalk_robot/request/body.py
dtalk_robot/request/constants.py
dtalk_robot/request/entity/__init__.py
dtalk_robot/request/entity/actioncard.py
dtalk_robot/request/entity/at.py
dtalk_robot/request/entity/btn.py
dtalk_robot/request/entity/feedcard.py
dtalk_robot/request/entity/link.py
dtalk_robot/request/entity/markdown.py
dtalk_robot/request/entity/text.py
dtalk_robot/response/__init__.py
dtalk_robot/response/body.py
dtalk_robot/robot.py
dtalk_robot-0.1.0.dist-info/LICENSE
dtalk_robot-0.1.0.dist-info/METADATA
dtalk_robot-0.1.0.dist-info/WHEEL
dtalk_robot-0.1.0.dist-info/RECORD
