Metadata-Version: 2.1
Name: dtalk_robot
Version: 0.1.0
Summary: 
Author: Yezhou
Requires-Python: >=3.11,<4.0
Classifier: Programming Language :: Python :: 3
Classifier: Programming Language :: Python :: 3.11
Classifier: Programming Language :: Python :: 3.12
Classifier: Programming Language :: Python :: 3.13
Requires-Dist: aiohttp (>=3.11.9,<4.0.0)
